{
    "Ar36": {
        "error": 0.001596581789237507, 
        "fit": "Parabolic", 
        "value": 0.4947297775006798
    }, 
    "Ar37": {
        "error": 0.012430180118614378, 
        "fit": "linear", 
        "value": 2.7056700853150133
    }, 
    "Ar38": {
        "error": 0.024698669548813064, 
        "fit": "linear", 
        "value": 0.11722953065291551
    }, 
    "Ar39": {
        "error": 0.024443543339012924, 
        "fit": "Parabolic", 
        "value": 2.8610531737946747
    }, 
    "Ar40": {
        "error": 0.03528906985992937, 
        "fit": "Parabolic", 
        "value": 167.49645090971842
    }
}